alu_4bit.v
module alu_4bit (
    input  wire [3:0] a,          // Operand A
    input  wire [3:0] b,          // Operand B
    input  wire [3:0] alu_sel,    // Operation select
    output reg  [3:0] result,     // ALU result
    output wire       zero,       // 1 if result == 0
    output wire       carry_out,  // carry out of adder
    output wire       overflow    // signed overflow
);

    localparam ALU_ADD  = 4'b0000;   // a + b
    localparam ALU_SUB  = 4'b0001;   // a - b
    localparam ALU_AND  = 4'b0010;   // a & b
    localparam ALU_OR   = 4'b0011;   // a | b
    localparam ALU_XOR  = 4'b0100;   // a ^ b
    localparam ALU_NOR  = 4'b0101;   // ~(a | b)
    localparam ALU_SLL  = 4'b0110;   // a << b[1:0]
    localparam ALU_SRL  = 4'b0111;   // a >> b[1:0]  (logical)
    localparam ALU_SLT  = 4'b1000;   // (a <  b) signed   -> 1 or 0
    localparam ALU_SLTU = 4'b1001;   // (a <  b) unsigned -> 1 or 0
    localparam ALU_PASS = 4'b1010;   // result = a (for LUI-style pass-through)

    // 5-bit wide internal sum so we can grab carry_out cleanly
    reg  [4:0] sum_ext;

    always @(*) begin
        sum_ext = 5'd0;
        case (alu_sel)
            ALU_ADD:  begin
                          sum_ext = {1'b0, a} + {1'b0, b};
                          result  = sum_ext[3:0];
                      end
            ALU_SUB:  begin
                          sum_ext = {1'b0, a} + {1'b0, ~b} + 5'd1; // a + (~b) + 1
                          result  = sum_ext[3:0];
                      end
            ALU_AND:  result = a & b;
            ALU_OR:   result = a | b;
            ALU_XOR:  result = a ^ b;
            ALU_NOR:  result = ~(a | b);
            ALU_SLL:  result = a << b[1:0];
            ALU_SRL:  result = a >> b[1:0];
            ALU_SLT:  result = ($signed(a) < $signed(b)) ? 4'd1 : 4'd0;
            ALU_SLTU: result = (a < b)                    ? 4'd1 : 4'd0;
            ALU_PASS: result = a;
            default:  result = 4'd0;
        endcase
    end

    assign zero      = (result == 4'd0);
    assign carry_out  = sum_ext[4];

    // when both operands have the same sign but the result's sign differs.
    assign overflow = ((alu_sel == ALU_ADD) && (a[3] == b[3]) && (result[3] != a[3])) ||
                       ((alu_sel == ALU_SUB) && (a[3] != b[3]) && (result[3] != a[3]));

endmodule

alu_4bit_tb.v
`timescale 1ns/1ps
`include "alu_4bit.v"

module alu_4bit_tb;

    reg  [3:0] a, b, alu_sel;
    wire [3:0] result;
    wire       zero, carry_out, overflow;

    integer errors = 0;
    integer tests  = 0;

    alu_4bit dut (
        .a(a),
        .b(b),
        .alu_sel(alu_sel),
        .result(result),
        .zero(zero),
        .carry_out(carry_out),
        .overflow(overflow)
    );
    initial begin
        $dumpfile("alu_4bit.vcd");
        $dumpvars(0, alu_4bit_tb);
    end
    task check(
        input [3:0] in_a,
        input [3:0] in_b,
        input [3:0] sel,
        input [3:0] expected,
        input [8*32-1:0] name   // human-readable label for the test (up to 32 chars)
    );
        begin
            a = in_a; b = in_b; alu_sel = sel;
            #5; // allow combinational logic to settle
            tests = tests + 1;
            if (result !== expected) begin
                errors = errors + 1;
                $display("[FAIL] %0s : a=%b b=%b sel=%b -> got %b, expected %b",
                          name, in_a, in_b, sel, result, expected);
            end else begin
                $display("[PASS] %0s : a=%b b=%b sel=%b -> %b",
                          name, in_a, in_b, sel, result);
            end
        end
    endtask
//testcases created by AI for all the ALU operations
    initial begin
        $display("---------------------------------------------------");
        $display(" Starting 4-bit ALU self-checking testbench");
        $display("---------------------------------------------------");

        // ADD: 3 + 4 = 7
        check(4'd3, 4'd4, 4'b0000, 4'd7,  "ADD 3+4");
        // ADD with overflow wraparound: 15 + 2 = 17 -> wraps to 1 (mod 16)
        check(4'd15, 4'd2, 4'b0000, 4'd1, "ADD wraparound 15+2");

        // SUB: 9 - 5 = 4
        check(4'd9, 4'd5, 4'b0001, 4'd4,  "SUB 9-5");
        // SUB negative result: 2 - 5 = -3 -> two's complement 4-bit = 1101
        check(4'd2, 4'd5, 4'b0001, 4'b1101, "SUB negative 2-5");

        // AND
        check(4'b1100, 4'b1010, 4'b0010, 4'b1000, "AND");
        // OR
        check(4'b1100, 4'b1010, 4'b0011, 4'b1110, "OR");
        // XOR
        check(4'b1100, 4'b1010, 4'b0100, 4'b0110, "XOR");
        // NOR
        check(4'b1100, 4'b0011, 4'b0101, 4'b0000, "NOR");

        // SLL: 1 << 2 = 4
        check(4'd1, 4'd2, 4'b0110, 4'd4, "SLL 1<<2");
        // SRL: 8 >> 2 = 2
        check(4'd8, 4'd2, 4'b0111, 4'd2, "SRL 8>>2");

        // SLT signed: -1 < 1  -> true (1)
        check(4'b1111, 4'b0001, 4'b1000, 4'd1, "SLT signed -1<1");
        // SLT signed: 3 < 1 -> false (0)
        check(4'd3, 4'd1, 4'b1000, 4'd0, "SLT signed 3<1");

        // SLTU: unsigned 15 < 1 -> false (0), since 1111=15 unsigned
        check(4'b1111, 4'b0001, 4'b1001, 4'd0, "SLTU 15<1 (unsigned)");

        // PASS
        check(4'd6, 4'd0, 4'b1010, 4'd6, "PASS a");

        $display("---------------------------------------------------");
        if (errors == 0)
            $display(" ALL %0d TESTS PASSED", tests);
        else
            $display(" %0d / %0d TESTS FAILED", errors, tests);
        $display("---------------------------------------------------");

        $finish;
    end

endmodule

alu_4bit.vcd
$date
	Tue Jul 07 19:55:02 2026
$end
$version
	Icarus Verilog
$end
$timescale
	1ps
$end
$scope module alu_4bit_tb $end
$var wire 1 ! zero $end
$var wire 4 " result [3:0] $end
$var wire 1 # overflow $end
$var wire 1 $ carry_out $end
$var reg 4 % a [3:0] $end
$var reg 4 & alu_sel [3:0] $end
$var reg 4 ' b [3:0] $end
$var integer 32 ( errors [31:0] $end
$var integer 32 ) tests [31:0] $end
$scope module dut $end
$var wire 4 * a [3:0] $end
$var wire 4 + alu_sel [3:0] $end
$var wire 4 , b [3:0] $end
$var wire 1 # overflow $end
$var wire 1 ! zero $end
$var wire 1 $ carry_out $end
$var parameter 4 - ALU_ADD $end
$var parameter 4 . ALU_AND $end
$var parameter 4 / ALU_NOR $end
$var parameter 4 0 ALU_OR $end
$var parameter 4 1 ALU_PASS $end
$var parameter 4 2 ALU_SLL $end
$var parameter 4 3 ALU_SLT $end
$var parameter 4 4 ALU_SLTU $end
$var parameter 4 5 ALU_SRL $end
$var parameter 4 6 ALU_SUB $end
$var parameter 4 7 ALU_XOR $end
$var reg 4 8 result [3:0] $end
$var reg 5 9 sum_ext [4:0] $end
$upscope $end
$scope task check $end
$var reg 4 : expected [3:0] $end
$var reg 4 ; in_a [3:0] $end
$var reg 4 < in_b [3:0] $end
$var reg 256 = name [255:0] $end
$var reg 4 > sel [3:0] $end
$upscope $end
$upscope $end
$enddefinitions $end
$comment Show the parameter values. $end
$dumpall
b100 7
b1 6
b111 5
b1001 4
b1000 3
b110 2
b1010 1
b11 0
b101 /
b10 .
b0 -
$end
#0
$dumpvars
b0 >
b1000001010001000100010000100000001100110010101100110100 =
b100 <
b11 ;
b111 :
b111 9
b111 8
b100 ,
b0 +
b11 *
b0 )
b0 (
b100 '
b0 &
b11 %
0$
0#
b111 "
0!
$end
#5000
0#
1$
b1 "
b1 8
b10001 9
b10 '
b10 ,
b1111 %
b1111 *
b1000001010001000100010000100000011101110111001001100001011100000110000101110010011011110111010101101110011001000010000000110001001101010010101100110010 =
b1 :
b10 <
b1111 ;
b1 )
#10000
1#
b100 "
b100 8
b10100 9
b1 &
b1 +
b101 '
b101 ,
b1001 %
b1001 *
b1010011010101010100001000100000001110010010110100110101 =
b100 :
b1 >
b101 <
b1001 ;
b10 )
#15000
0#
0$
b1101 "
b1101 8
b1101 9
b10 %
b10 *
b1010011010101010100001000100000011011100110010101100111011000010111010001101001011101100110010100100000001100100010110100110101 =
b1101 :
b10 ;
b11 )
#20000
b1000 "
b1000 8
b0 9
b10 &
b10 +
b1010 '
b1010 ,
b1100 %
b1100 *
b10000010100111001000100 =
b1000 :
b10 >
b1010 <
b1100 ;
b100 )
#25000
b1110 "
b1110 8
b11 &
b11 +
b100111101010010 =
b1110 :
b11 >
b101 )
#30000
b110 "
b110 8
b100 &
b100 +
b10110000100111101010010 =
b110 :
b100 >
b110 )
#35000
1!
b0 "
b0 8
b101 &
b101 +
b11 '
b11 ,
b10011100100111101010010 =
b0 :
b101 >
b11 <
b111 )
#40000
0!
b100 "
b100 8
b110 &
b110 +
b10 '
b10 ,
b1 %
b1 *
b101001101001100010011000010000000110001001111000011110000110010 =
b100 :
b110 >
b10 <
b1 ;
b1000 )
#45000
b10 "
b10 8
b111 &
b111 +
b1000 %
b1000 *
b101001101010010010011000010000000111000001111100011111000110010 =
b10 :
b111 >
b1000 ;
b1001 )
#50000
b1 "
b1 8
b1000 &
b1000 +
b1 '
b1 ,
b1111 %
b1111 *
b10100110100110001010100001000000111001101101001011001110110111001100101011001000010000000101101001100010011110000110001 =
b1 :
b1000 >
b1 <
b1111 ;
b1010 )
#55000
1!
b0 "
b0 8
b11 %
b11 *
b101001101001100010101000010000001110011011010010110011101101110011001010110010000100000001100110011110000110001 =
b0 :
b11 ;
b1011 )
#60000
b1001 &
b1001 +
b1111 %
b1111 *
b101001101001100010101000101010100100000001100010011010100111100001100010010000000101000011101010110111001110011011010010110011101101110011001010110010000101001 =
b1001 >
b1111 ;
b1100 )
#65000
0!
b110 "
b110 8
b1010 &
b1010 +
b0 '
b0 ,
b110 %
b110 *
b10100000100000101010011010100110010000001100001 =
b110 :
b1010 >
b0 <
b110 ;
b1101 )
#70000
b1110 )
